src/__init__.py
src/command.py
src/commons.py
src/create_proxy.py
mtgproxy-0.1.0.dist-info/entry_points.txt
mtgproxy-0.1.0.dist-info/LICENSE
mtgproxy-0.1.0.dist-info/WHEEL
mtgproxy-0.1.0.dist-info/METADATA
mtgproxy-0.1.0.dist-info/RECORD
