Metadata-Version: 2.1
Name: mtgproxy
Version: 0.1.0
Summary: This is the scripts for automatically creating a proxy from the deck list.
Home-page: https://github.com/reonyanarticle/mtg_proxy
License: MIT
Author: reonyanarticle
Author-email: reonaarticles@gmail.com
Requires-Python: >=3.9,<4.0
Classifier: License :: OSI Approved :: MIT License
Classifier: Programming Language :: Python :: 3
Classifier: Programming Language :: Python :: 3.9
Requires-Dist: Pillow (>=8.3.2,<9.0.0)
Requires-Dist: click (>=8.0.1,<9.0.0)
Requires-Dist: more-itertools (>=8.10.0,<9.0.0)
Requires-Dist: mtgsdk (>=1.3.1,<2.0.0)
Requires-Dist: reportlab (>=3.6.1,<4.0.0)
Requires-Dist: tqdm (>=4.62.3,<5.0.0)
Project-URL: Repository, https://github.com/reonyanarticle/mtg_proxy
